django_simple_factory/__init__.py
django_simple_factory/apps.py
django_simple_factory/factories.py
django_simple_factory/mixins.py
django_simple_factory/tests.py
django_simple_factory/migrations/__init__.py
django_simple_factory-0.3.3.dist-info/licenses/LICENSE
django_simple_factory-0.3.3.dist-info/WHEEL
django_simple_factory-0.3.3.dist-info/METADATA
django_simple_factory-0.3.3.dist-info/RECORD
