Metadata-Version: 2.4
Name: django-simple-factory
Version: 0.3.3
Summary: A simple factory for Django Applications
Author-email: Ian Kollipara <ian.kollipara@cune.edu>
Requires-Python: >=3.11
Classifier: Programming Language :: Python :: 3
Classifier: License :: OSI Approved :: MIT License
Classifier: Operating System :: OS Independent
License-File: LICENSE
Requires-Dist: django
Requires-Dist: Faker
Project-URL: Bug Tracker, https://github.com/ikollipara/django-simple-factory/issues
Project-URL: Homepage, https://github.com/ikollipara/django-simple-factory
